phase_gate.v
module CustomInstrument (
    input wire clk,
    input wire reset,
    input wire [31:0] sync,
    input wire signed [15:0] inputa,
    input wire signed [15:0] inputb,
    input wire signed [15:0] inputc,
    input wire signed [15:0] inputd,
    input wire exttrig,
    output wire signed [15:0] outputa,
    output wire signed [15:0] outputb,
    output wire signed [15:0] outputc,
    output wire signed [15:0] outputd,
    input wire [31:0] control [0:15],
    output wire [31:0] status[0:15]
);
    parameter N_LOOP       = 3989;
    parameter N_TIME_BIN   = 2;
    parameter N_SW         = 4;
    parameter N_DELAY      = 100;
    parameter N_SWITCH_LEN = N_LOOP / N_TIME_BIN;   // 1994
    parameter N_MZI        = N_LOOP;
    parameter N_EXPT       = N_LOOP + N_MZI;         // 7978
    parameter BRANCH_POINT = N_LOOP;                 // = 3989
    parameter SW1_SEQUENCE = 4'b0100;
    parameter SW2_SEQUENCE = 4'b0001;

    // ── Atom cavity period (independent toggle) ───────────────────
    // Adjust N_ATOM_PERIOD to set how often atom_cavity toggles.
    parameter N_ATOM_PERIOD = 2500;

    // ── Registers ────────────────────────────────────────────────
    reg [31:0] clk_counter   = 0;
    reg [1:0]  tb_idx        = 0;
    reg [31:0] slot_counter  = 0;
    reg        sw1, sw2, sw3;

    reg        atom_cavity   = 0;   // 1-bit: independent periodic signal
    reg [15:0] photon_phase  = 0;   // 16-bit: phase in discrete multiples of pi
    reg [31:0] atom_counter  = 0;   // drives atom_cavity toggle

    // ── Combinational: sw3 window ─────────────────────────────────
    wire sw3_on_window = (clk_counter >= (N_SW-1)*N_SWITCH_LEN - N_DELAY) &&
                         (clk_counter <  N_EXPT - N_DELAY);

    // ── Sequential logic ──────────────────────────────────────────
    always @(posedge clk or posedge reset) begin
        if (reset) begin
            clk_counter  <= 0;
            slot_counter <= 0;
            tb_idx       <= 0;
            sw1 <= 0; sw2 <= 0; sw3 <= 0;

            atom_cavity  <= 0;
            atom_counter <= 0;
            photon_phase <= 0;
        end else begin

            // ── atom_cavity: independent periodic toggle ────────────
            if (atom_counter >= N_ATOM_PERIOD - 1) begin
                atom_counter <= 0;
                atom_cavity  <= ~atom_cavity;
            end else begin
                atom_counter <= atom_counter + 1;
            end

            // ── photon_phase accumulation at BRANCH_POINT ───────────
            // At every cycle where clk_counter == BRANCH_POINT:
            //   - if atom_cavity is HIGH  → skip (no phase added)
            //   - otherwise               → add 1 (one unit of pi)
            if (clk_counter == BRANCH_POINT) begin
                if (atom_cavity) begin
                    photon_phase <= photon_phase + 16'd1;
                end
                // else: atom_cavity high → hold phase
            end

            // ── Advance slot counter; roll tb_idx at each boundary ──
            if (slot_counter >= N_SWITCH_LEN - 1) begin
                slot_counter <= 0;
                tb_idx       <= (tb_idx >= N_SW - 1) ? 2'd0 : tb_idx + 1'd1;
            end else begin
                slot_counter <= slot_counter + 1;
            end

            // ── Full experiment cycle reset ─────────────────────────
            if (clk_counter >= N_EXPT - 1) begin
                clk_counter  <= 0;
                slot_counter <= 0;
                tb_idx       <= 0;
            end else begin
                clk_counter <= clk_counter + 1;
            end

            // ── Switch outputs ──────────────────────────────────────
            sw1 <= SW1_SEQUENCE[N_SW - 1 - tb_idx];
            sw2 <= SW2_SEQUENCE[N_SW - 1 - tb_idx];
            sw3 <= sw3_on_window;
        end
    end

    // ── Output assignments ────────────────────────────────────────
    assign outputa = sw1 ? 16'h7FFF : 16'h0000;
    assign outputb = sw2 ? 16'h7FFF : 16'h0000;
    assign outputc = sw3 ? 16'h7FFF : 16'h0000;
    assign outputd = 16'b0;

endmodule

phase_gate_tb.v
`timescale 1ns/1ps

module CustomInstrument_tb;

    // ── DUT ports ─────────────────────────────────────────────────
    reg         clk    = 0;
    reg         reset  = 1;
    reg  [31:0] sync   = 0;
    reg  signed [15:0] inputa = 0, inputb = 0, inputc = 0, inputd = 0;
    reg         exttrig = 0;
    wire signed [15:0] outputa, outputb, outputc, outputd;
    reg  [31:0] control[0:15];
    wire [31:0] status[0:15];

    // ── Parameters (mirror DUT) ───────────────────────────────────
    localparam N_LOOP        = 3989;
    localparam N_TIME_BIN    = 2;
    localparam N_SW          = 4;
    localparam N_DELAY       = 100;
    localparam N_SWITCH_LEN  = N_LOOP / N_TIME_BIN;  // 1994
    localparam N_MZI         = N_LOOP;
    localparam N_EXPT        = N_LOOP + N_MZI;        // 7978
    localparam BRANCH_POINT  = N_LOOP;                // 3989
    localparam N_ATOM_PERIOD = 2500;
    localparam N_CYCLES      = 3;  // full experiment cycles to simulate

    // ── Clock: 10 ns period ───────────────────────────────────────
    always #5 clk = ~clk;
    
    // ── DUT instantiation ─────────────────────────────────────────
    CustomInstrument #(
        .N_LOOP       (N_LOOP),
        .N_TIME_BIN   (N_TIME_BIN),
        .N_SW         (N_SW),
        .N_DELAY      (N_DELAY),
        .N_ATOM_PERIOD(N_ATOM_PERIOD)
    ) dut (
        .clk      (clk),
        .reset    (reset),
        .sync     (sync),
        .inputa   (inputa),
        .inputb   (inputb),
        .inputc   (inputc),
        .inputd   (inputd),
        .exttrig  (exttrig),
        .outputa  (outputa),
        .outputb  (outputb),
        .outputc  (outputc),
        .outputd  (outputd),
        .control  (control),
        .status   (status)
    );

    // ── Tracking variables ────────────────────────────────────────
    integer cycle_num = 0;
    integer branch_hits      = 0;   // times we reached BRANCH_POINT
    integer phase_increments = 0;   // times phase was actually added
    integer phase_skips      = 0;   // times atom_cavity blocked the add

    reg [15:0] prev_photon_phase = 0;
    reg        prev_atom_cavity  = 0;
    reg [31:0] prev_clk_counter  = 0;

    // ── Capture internal signals via hierarchical references ──────
    wire [31:0] clk_counter  = dut.clk_counter;
    wire [15:0] photon_phase = dut.photon_phase;
    wire        atom_cavity  = dut.atom_cavity;
    wire [31:0] atom_counter = dut.atom_counter;
    wire [1:0]  tb_idx       = dut.tb_idx;
    wire [31:0] slot_counter = dut.slot_counter;

    wire expected_sw3 = (clk_counter >= (N_SW-1)*N_SWITCH_LEN - N_DELAY) &&
                         (clk_counter <  N_EXPT - N_DELAY);

    // ── Task: print a timestamped info line ───────────────────────
    task print_state(input [127:0] tag);
        $display("[%0t ns] %s | clk_ctr=%0d tb_idx=%0d slot=%0d | atom_cav=%b atom_ctr=%0d | photon_phase=%0d | sw1=%b sw2=%b sw3=%b",
            $time, tag,
            clk_counter, tb_idx, slot_counter,
            atom_cavity, atom_counter,
            photon_phase,
            outputa[15], outputb[15], outputc[15]);
    endtask

    // ── Main stimulus ─────────────────────────────────────────────
    integer i;
    initial begin
        // Initialise control
        for (i = 0; i < 16; i++) control[i] = 32'h0;

        // ── Reset pulse ───────────────────────────────────────────
        reset = 1;
        repeat(4) @(posedge clk);
        @(negedge clk);
        reset = 0;
        $display("[%0t ns] Reset released", $time);

        // ── Run for N_CYCLES complete experiment cycles ───────────
        repeat(N_CYCLES * N_EXPT) begin
            @(posedge clk);
            #1; // sample just after posedge so registered values have settled

            // ── Detect experiment cycle wrap ──────────────────────
            if (clk_counter == 0 && prev_clk_counter == N_EXPT - 1) begin
                cycle_num++;
                $display("\n━━━ Experiment cycle %0d complete ━━━", cycle_num);
                $display("    Branch hits this cycle      : tracked cumulatively");
                $display("    Total phase increments so far: %0d", phase_increments);
                $display("    Total phase skips so far     : %0d", phase_skips);
            end

            // ── Detect BRANCH_POINT ───────────────────────────────
            if (prev_clk_counter == BRANCH_POINT) begin
                branch_hits++;
                if (photon_phase != prev_photon_phase) begin
                    phase_increments++;
                    $display("[%0t ns] BRANCH_POINT: atom_cavity=%b → phase %0d→%0d (+1)",
                        $time, prev_atom_cavity, prev_photon_phase, photon_phase);
                end else begin
                    phase_skips++;
                    $display("[%0t ns] BRANCH_POINT: atom_cavity=%b → phase HELD at %0d",
                        $time, prev_atom_cavity, photon_phase);
                end
            end

            // ── Check: phase should only ever change at BRANCH_POINT ──
            if (photon_phase != prev_photon_phase && prev_clk_counter != BRANCH_POINT) begin
                $error("[%0t ns] FAIL: photon_phase changed outside BRANCH_POINT (clk_ctr=%0d, %0d→%0d)",
                    $time, prev_clk_counter, prev_photon_phase, photon_phase);
            end

            // ── Check: phase increments by at most 1 ─────────────
            if (photon_phase - prev_photon_phase > 1 && photon_phase > prev_photon_phase) begin
                $error("[%0t ns] FAIL: photon_phase jumped by >1 (clk_ctr=%0d, %0d→%0d)",
                    $time, prev_clk_counter, prev_photon_phase, photon_phase);
            end

            // ── Check: sw3 is high only in the sw3_on_window ─────
            begin

                if (outputc[15] !== expected_sw3)
                $error("[%0t ns] FAIL: sw3 mismatch at clk_ctr=%0d (got %b, expected %b)",
                    $time, prev_clk_counter, outputc[15], expected_sw3);
            end

            // ── Snapshot key moments each cycle ──────────────────
            if (clk_counter == 0    ||
                clk_counter == 1    ||
                clk_counter == BRANCH_POINT - 1 ||
                clk_counter == BRANCH_POINT     ||
                clk_counter == BRANCH_POINT + 1 ||
                clk_counter == N_EXPT - N_DELAY ||
                clk_counter == N_EXPT - 1)
                print_state("SNAP");

            // ── Save previous values ──────────────────────────────
            prev_clk_counter  <= clk_counter;
            prev_photon_phase <= photon_phase;
            prev_atom_cavity  <= atom_cavity;
        end

        // ── Final summary ─────────────────────────────────────────
        $display("\n══════════════════════════════════════════");
        $display("  Simulation complete — %0d experiment cycles", N_CYCLES);
        $display("  Total BRANCH_POINT events : %0d", branch_hits);
        $display("  Phase increments          : %0d", phase_increments);
        $display("  Phase skips (atom_cav=1)  : %0d", phase_skips);
        $display("  Final photon_phase value  : %0d × π", photon_phase);

        // ── Sanity check: increments + skips == branch_hits ──────
        if (phase_increments + phase_skips !== branch_hits)
            $error("FAIL: increments (%0d) + skips (%0d) != branch_hits (%0d)",
                phase_increments, phase_skips, branch_hits);
        else
            $display("  PASS: increments + skips == branch_hits ✓");

        $display("══════════════════════════════════════════\n");
        $finish;
    end

    // ── Waveform dump ─────────────────────────────────────────────
    initial begin
        $dumpfile("custom_instrument.vcd");
        $dumpvars(0, CustomInstrument_tb);
    end

endmodule

custom_instrument.vcd
$date
	Sat Apr 11 14:37:39 2026
$end
$version
	Icarus Verilog
$end
$timescale
	1ps
$end
$scope module CustomInstrument_tb $end
$var wire 1 ! atom_cavity $end
$var wire 32 " atom_counter [31:0] $end
$var wire 32 # clk_counter [31:0] $end
$var wire 1 $ expected_sw3 $end
$var wire 16 % outputd [15:0] $end
$var wire 16 & photon_phase [15:0] $end
$var wire 32 ' slot_counter [31:0] $end
$var wire 2 ( tb_idx [1:0] $end
$var wire 16 ) outputc [15:0] $end
$var wire 16 * outputb [15:0] $end
$var wire 16 + outputa [15:0] $end
$var parameter 32 , BRANCH_POINT $end
$var parameter 32 - N_ATOM_PERIOD $end
$var parameter 32 . N_CYCLES $end
$var parameter 32 / N_DELAY $end
$var parameter 33 0 N_EXPT $end
$var parameter 32 1 N_LOOP $end
$var parameter 32 2 N_MZI $end
$var parameter 32 3 N_SW $end
$var parameter 32 4 N_SWITCH_LEN $end
$var parameter 32 5 N_TIME_BIN $end
$var reg 1 6 clk $end
$var reg 1 7 exttrig $end
$var reg 16 8 inputa [15:0] $end
$var reg 16 9 inputb [15:0] $end
$var reg 16 : inputc [15:0] $end
$var reg 16 ; inputd [15:0] $end
$var reg 1 < prev_atom_cavity $end
$var reg 32 = prev_clk_counter [31:0] $end
$var reg 16 > prev_photon_phase [15:0] $end
$var reg 1 ? reset $end
$var reg 32 @ sync [31:0] $end
$var integer 32 A branch_hits [31:0] $end
$var integer 32 B cycle_num [31:0] $end
$var integer 32 C i [31:0] $end
$var integer 32 D phase_increments [31:0] $end
$var integer 32 E phase_skips [31:0] $end
$scope module dut $end
$var wire 1 6 clk $end
$var wire 1 7 exttrig $end
$var wire 16 F inputa [15:0] $end
$var wire 16 G inputb [15:0] $end
$var wire 16 H inputc [15:0] $end
$var wire 16 I inputd [15:0] $end
$var wire 16 J outputd [15:0] $end
$var wire 1 ? reset $end
$var wire 1 K sw3_on_window $end
$var wire 32 L sync [31:0] $end
$var wire 16 M outputc [15:0] $end
$var wire 16 N outputb [15:0] $end
$var wire 16 O outputa [15:0] $end
$var parameter 32 P BRANCH_POINT $end
$var parameter 32 Q N_ATOM_PERIOD $end
$var parameter 32 R N_DELAY $end
$var parameter 33 S N_EXPT $end
$var parameter 32 T N_LOOP $end
$var parameter 32 U N_MZI $end
$var parameter 32 V N_SW $end
$var parameter 32 W N_SWITCH_LEN $end
$var parameter 32 X N_TIME_BIN $end
$var parameter 4 Y SW1_SEQUENCE $end
$var parameter 4 Z SW2_SEQUENCE $end
$var reg 1 [ atom_cavity $end
$var reg 32 \ atom_counter [31:0] $end
$var reg 32 ] clk_counter [31:0] $end
$var reg 16 ^ photon_phase [15:0] $end
$var reg 32 _ slot_counter [31:0] $end
$var reg 1 ` sw1 $end
$var reg 1 a sw2 $end
$var reg 1 b sw3 $end
$var reg 2 c tb_idx [1:0] $end
$upscope $end
$scope task print_state $end
$var reg 128 d tag [127:0] $end
$upscope $end
$upscope $end
$enddefinitions $end
$comment Show the parameter values. $end
$dumpall
b1 Z
b100 Y
b10 X
b11111001010 W
b100 V
b111110010101 U
b111110010101 T
b1111100101010 S
b1100100 R
b100111000100 Q
b111110010101 P
b10 5
b11111001010 4
b100 3
b111110010101 2
b111110010101 1
b1111100101010 0
b1100100 /
b11 .
b100111000100 -
b111110010101 ,
$end
#0
$dumpvars
bx d
b0 c
xb
xa
x`
b0 _
b0 ^
b0 ]
b0 \
0[
b0xxxxxxxxxxxxxxx O
b0xxxxxxxxxxxxxxx N
b0xxxxxxxxxxxxxxx M
b0 L
0K
b0 J
b0 I
b0 H
b0 G
b0 F
b0 E
b0 D
b10000 C
b0 B
b0 A
b0 @
1?
b0 >
b0 =
0<
b0 ;
b0 :
b0 9
b0 8
07
06
b0xxxxxxxxxxxxxxx +
b0xxxxxxxxxxxxxxx *
b0xxxxxxxxxxxxxxx )
b0 (
b0 '
b0 &
b0 %
0$
b0 #
b0 "
0!
$end
#5000
b0 )
b0 M
b0 *
b0 N
b0 +
b0 O
0b
0a
0`
16
#10000
06
#15000
16
#20000
06
#25000
16
#30000
06
#35000
16
#40000
0?
06
#45000
b1 #
b1 ]
b1 '
b1 _
b1 "
b1 \
16
#46000
b1 =
b1010011010011100100000101010000 d
#50000
06
#55000
b10 #
b10 ]
b10 '
b10 _
b10 "
b10 \
16
#56000
b10 =
#60000
06
#65000
b11 #
b11 ]
b11 '
b11 _
b11 "
b11 \
16
#66000
b11 =
#70000
06
#75000
b100 #
b100 ]
b100 '
b100 _
b100 "
b100 \
16
#76000
b100 =
#80000
06
#85000
b101 #
b101 ]
b101 '
b101 _
b101 "
b101 \
16
#86000
b101 =
#90000
06
#95000
b110 #
b110 ]
b110 '
b110 _
b110 "
b110 \
16
#96000
b110 =
#100000
06
#105000
b111 #
b111 ]
b111 '
b111 _
b111 "
b111 \
16
#106000
b111 =
#110000
06
#115000
b1000 #
b1000 ]
b1000 '
b1000 _
b1000 "
b1000 \
16
#116000
b1000 =
#120000
06
#125000
b1001 #
b1001 ]
b1001 '
b1001 _
b1001 "
b1001 \
16
#126000
b1001 =
#130000
06
#135000
b1010 #
b1010 ]
b1010 '
b1010 _
b1010 "
b1010 \
16
#136000
b1010 =
#140000
06
#145000
b1011 #
b1011 ]
b1011 '
b1011 _
b1011 "
b1011 \
16
#146000
b1011 =
#150000
06
#155000
b1100 #
b1100 ]
b1100 '
b1100 _
b1100 "
b1100 \
16
#156000
b1100 =
#160000
06
#165000
b1101 #
b1101 ]
b1101 '
b1101 _
b1101 "
b1101 \
16
#166000
b1101 =
#170000
06
#175000
b1110 #
b1110 ]
b1110 '
b1110 _
b1110 "
b1110 \
16
#176000
b1110 =
#180000
06
#185000
b1111 #
b1111 ]
b1111 '
b1111 _
b1111 "
b1111 \
16
#186000
b1111 =
#190000
06
#195000
b10000 #
b10000 ]
b10000 '
b10000 _
b10000 "
b10000 \
16
#196000
b10000 =
#200000
06
#205000
b10001 #
b10001 ]
b10001 '
b10001 _
b10001 "
b10001 \
16
#206000
b10001 =
#210000
06
#215000
b10010 #
b10010 ]
b10010 '
b10010 _
b10010 "
b10010 \
16
#216000
b10010 =
#220000
06
#225000
b10011 #
b10011 ]
b10011 '
b10011 _
b10011 "
b10011 \
16
#226000
b10011 =
#230000
06
#235000
b10100 #
b10100 ]
b10100 '
b10100 _
b10100 "
b10100 \
16
#236000
b10100 =
#240000
06
#245000
b10101 #
b10101 ]
b10101 '
b10101 _
b10101 "
b10101 \
16
#246000
b10101 =
#250000
06
#255000
b10110 #
b10110 ]
b10110 '
b10110 _
b10110 "
b10110 \
16
#256000
b10110 =
#260000
06
#265000
b10111 #
b10111 ]
b10111 '
b10111 _
b10111 "
b10111 \
16
#266000
b10111 =
#270000
06
#275000
b11000 #
b11000 ]
b11000 '
b11000 _
b11000 "
b11000 \
16
#276000
b11000 =
#280000
06
#285000
b11001 #
b11001 ]
b11001 '
b11001 _
b11001 "
b11001 \
16
#286000
b11001 =
#290000
06
#295000
b11010 #
b11010 ]
b11010 '
b11010 _
b11010 "
b11010 \
16
#296000
b11010 =
#300000
06
#305000
b11011 #
b11011 ]
b11011 '
b11011 _
b11011 "
b11011 \
16
#306000
b11011 =
#310000
06
#315000
b11100 #
b11100 ]
b11100 '
b11100 _
b11100 "
b11100 \
16
#316000
b11100 =
#320000
06
#325000
b11101 #
b11101 ]
b11101 '
b11101 _
b11101 "
b11101 \
16
#326000
b11101 =
#330000
06
#335000
b11110 #
b11110 ]
b11110 '
b11110 _
b11110 "
b11110 \
16
#336000
b11110 =
#340000
06
#345000
b11111 #
b11111 ]
b11111 '
b11111 _
b11111 "
b11111 \
16
#346000
b11111 =
#350000
06
#355000
b100000 #
b100000 ]
b100000 '
b100000 _
b100000 "
b100000 \
16
#356000
b100000 =
#360000
06
#365000
b100001 #
b100001 ]
b100001 '
b100001 _
b100001 "
b100001 \
16
#366000
b100001 =
#370000
06
#375000
b100010 #
b100010 ]
b100010 '
b100010 _
b100010 "
b100010 \
16
#376000
b100010 =
#380000
06
#385000
b100011 #
b100011 ]
b100011 '
b100011 _
b100011 "
b100011 \
16
#386000
b100011 =
#390000
06
#395000
b100100 #
b100100 ]
b100100 '
b100100 _
b100100 "
b100100 \
16
#396000
b100100 =
#400000
06
#405000
b100101 #
b100101 ]
b100101 '
b100101 _
b100101 "
b100101 \
16
#406000
b100101 =
#410000
06
#415000
b100110 #
b100110 ]
b100110 '
b100110 _
b100110 "
b100110 \
16
#416000
b100110 =
#420000
06
#425000
b100111 #
b100111 ]
b100111 '
b100111 _
b100111 "
b100111 \
16
#426000
b100111 =
#430000
06
#435000
b101000 #
b101000 ]
b101000 '
b101000 _
b101000 "
b101000 \
16
#436000
b101000 =
#440000
06
#445000
b101001 #
b101001 ]
b101001 '
b101001 _
b101001 "
b101001 \
16
#446000
b101001 =
#450000
06
#455000
b101010 #
b101010 ]
b101010 '
b101010 _
b101010 "
b101010 \
16
#456000
b101010 =
#460000
06
#465000
b101011 #
b101011 ]
b101011 '
b101011 _
b101011 "
b101011 \
16
#466000
b101011 =
#470000
06
#475000
b101100 #
b101100 ]
b101100 '
b101100 _
b101100 "
b101100 \
16
#476000
b101100 =
#480000
06
#485000
b101101 #
b101101 ]
b101101 '
b101101 _
b101101 "
b101101 \
16
#486000
b101101 =
#490000
06
#495000
b101110 #
b101110 ]
b101110 '
b101110 _
b101110 "
b101110 \
16
#496000
b101110 =
#500000
06
#505000
b101111 #
b101111 ]
b101111 '
b101111 _
b101111 "
b101111 \
16
#506000
b101111 =
#510000
06
#515000
b110000 #
b110000 ]
b110000 '
b110000 _
b110000 "
b110000 \
16
#516000
b110000 =
#520000
06
#525000
b110001 #
b110001 ]
b110001 '
b110001 _
b110001 "
b110001 \
16
#526000
b110001 =
#530000
06
#535000
b110010 #
b110010 ]
b110010 '
b110010 _
b110010 "
b110010 \
16
#536000
b110010 =
#540000
06
#545000
b110011 #
b110011 ]
b110011 '
b110011 _
b110011 "
b110011 \
16
#546000
b110011 =
#550000
06
#555000
b110100 #
b110100 ]
b110100 '
b110100 _
b110100 "
b110100 \
16
#556000
b110100 =
#560000
06
#565000
b110101 #
b110101 ]
b110101 '
b110101 _
b110101 "
b110101 \
16
#566000
b110101 =
#570000
06
#575000
b110110 #
b110110 ]
b110110 '
b110110 _
b110110 "
b110110 \
16
#576000
b110110 =
#580000
06
#585000
b110111 #
b110111 ]
b110111 '
b110111 _
b110111 "
b110111 \
16
#586000
b110111 =
#590000
06
#595000
b111000 #
b111000 ]
b111000 '
b111000 _
b111000 "
b111000 \
16
#596000
b111000 =
#600000
06
#605000
b111001 #
b111001 ]
b111001 '
b111001 _
b111001 "
b111001 \
16
#606000
b111001 =
#610000
06
#615000
b111010 #
b111010 ]
b111010 '
b111010 _
b111010 "
b111010 \
16
#616000
b111010 =
#620000
06
#625000
b111011 #
b111011 ]
b111011 '
b111011 _
b111011 "
b111011 \
16
#626000
b111011 =
#630000
06
#635000
b111100 #
b111100 ]
b111100 '
b111100 _
b111100 "
b111100 \
16
#636000
b111100 =
#640000
06
#645000
b111101 #
b111101 ]
b111101 '
b111101 _
b111101 "
b111101 \
16
#646000
b111101 =
#650000
06
#655000
b111110 #
b111110 ]
b111110 '
b111110 _
b111110 "
b111110 \
16
#656000
b111110 =
#660000
06
#665000
b111111 #
b111111 ]
b111111 '
b111111 _
b111111 "
b111111 \
16
#666000
b111111 =
#670000
06
#675000
b1000000 #
b1000000 ]
b1000000 '
b1000000 _
b1000000 "
b1000000 \
16
#676000
b1000000 =
#680000
06
#685000
b1000001 #
b1000001 ]
b1000001 '
b1000001 _
b1000001 "
b1000001 \
16
#686000
b1000001 =
#690000
06
#695000
b1000010 #
b1000010 ]
b1000010 '
b1000010 _
b1000010 "
b1000010 \
16
#696000
b1000010 =
#700000
06
#705000
b1000011 #
b1000011 ]
b1000011 '
b1000011 _
b1000011 "
b1000011 \
16
#706000
b1000011 =
#710000
06
#715000
b1000100 #
b1000100 ]
b1000100 '
b1000100 _
b1000100 "
b1000100 \
16
#716000
b1000100 =
#720000
06
#725000
b1000101 #
b1000101 ]
b1000101 '
b1000101 _
b1000101 "
b1000101 \
16
#726000
b1000101 =
#730000
06
#735000
b1000110 #
b1000110 ]
b1000110 '
b1000110 _
b1000110 "
b1000110 \
16
#736000
b1000110 =
#740000
06
#745000
b1000111 #
b1000111 ]
b1000111 '
b1000111 _
b1000111 "
b1000111 \
16
#746000
b1000111 =
#750000
06
#755000
b1001000 #
b1001000 ]
b1001000 '
b1001000 _
b1001000 "
b1001000 \
16
#756000
b1001000 =
#760000
06
#765000
b1001001 #
b1001001 ]
b1001001 '
b1001001 _
b1001001 "
b1001001 \
16
#766000
b1001001 =
#770000
06
#775000
b1001010 #
b1001010 ]
b1001010 '
b1001010 _
b1001010 "
b1001010 \
16
#776000
b1001010 =
#780000
06
#785000
b1001011 #
b1001011 ]
b1001011 '
b1001011 _
b1001011 "
b1001011 \
16
#786000
b1001011 =
#790000
06
#795000
b1001100 #
b1001100 ]
b1001100 '
b1001100 _
b1001100 "
b1001100 \
16
#796000
b1001100 =
#800000
06
#805000
b1001101 #
b1001101 ]
b1001101 '
b1001101 _
b1001101 "
b1001101 \
16
#806000
b1001101 =
#810000
06
#815000
b1001110 #
b1001110 ]
b1001110 '
b1001110 _
b1001110 "
b1001110 \
16
#816000
b1001110 =
#820000
06
#825000
b1001111 #
b1001111 ]
b1001111 '
b1001111 _
b1001111 "
b1001111 \
16
#826000
b1001111 =
#830000
06
#835000
b1010000 #
b1010000 ]
b1010000 '
b1010000 _
b1010000 "
b1010000 \
16
#836000
b1010000 =
#840000
06
#845000
b1010001 #
b1010001 ]
b1010001 '
b1010001 _
b1010001 "
b1010001 \
16
#846000
b1010001 =
#850000
06
#855000
b1010010 #
b1010010 ]
b1010010 '
b1010010 _
b1010010 "
b1010010 \
16
#856000
b1010010 =
#860000
06
#865000
b1010011 #
b1010011 ]
b1010011 '
b1010011 _
b1010011 "
b1010011 \
16
#866000
b1010011 =
#870000
06
#875000
b1010100 #
b1010100 ]
b1010100 '
b1010100 _
b1010100 "
b1010100 \
16
#876000
b1010100 =
#880000
06
#885000
b1010101 #
b1010101 ]
b1010101 '
b1010101 _
b1010101 "
b1010101 \
16
#886000
b1010101 =
#890000
06
#895000
b1010110 #
b1010110 ]
b1010110 '
b1010110 _
b1010110 "
b1010110 \
16
#896000
b1010110 =
#900000
06
#905000
b1010111 #
b1010111 ]
b1010111 '
b1010111 _
b1010111 "
b1010111 \
16
#906000
b1010111 =
#910000
06
#915000
b1011000 #
b1011000 ]
b1011000 '
b1011000 _
b1011000 "
b1011000 \
16
#916000
b1011000 =
#920000
06
#925000
b1011001 #
b1011001 ]
b1011001 '
b1011001 _
b1011001 "
b1011001 \
16
#926000
b1011001 =
#930000
06
#935000
b1011010 #
b1011010 ]
b1011010 '
b1011010 _
b1011010 "
b1011010 \
16
#936000
b1011010 =
#940000
06
#945000
b1011011 #
b1011011 ]
b1011011 '
b1011011 _
b1011011 "
b1011011 \
16
#946000
b1011011 =
#950000
06
#955000
b1011100 #
b1011100 ]
b1011100 '
b1011100 _
b1011100 "
b1011100 \
16
#956000
b1011100 =
#960000
06
#965000
b1011101 #
b1011101 ]
b1011101 '
b1011101 _
b1011101 "
b1011101 \
16
#966000
b1011101 =
#970000
06
#975000
b1011110 #
b1011110 ]
b1011110 '
b1011110 _
b1011110 "
b1011110 \
16
#976000
b1011110 =
#980000
06
#985000
b1011111 #
b1011111 ]
b1011111 '
b1011111 _
b1011111 "
b1011111 \
16
#986000
b1011111 =
#990000
06
#995000
b1100000 #
b1100000 ]
b1100000 '
b1100000 _
b1100000 "
b1100000 \
16
#996000
b1100000 =
#1000000
06
#1005000
b1100001 #
b1100001 ]
b1100001 '
b1100001 _
b1100001 "
b1100001 \
16
#1006000
b1100001 =
#1010000
06
#1015000
b1100010 #
b1100010 ]
b1100010 '
b1100010 _
b1100010 "
b1100010 \
16
#1016000
b1100010 =
#1020000
06
#1025000
b1100011 #
b1100011 ]
b1100011 '
b1100011 _
b1100011 "
b1100011 \
16
#1026000
b1100011 =
#1030000
06
#1035000
b1100100 #
b1100100 ]
b1100100 '
b1100100 _
b1100100 "
b1100100 \
16
#1036000
b1100100 =
#1040000
06
#1045000
b1100101 #
b1100101 ]
b1100101 '
b1100101 _
b1100101 "
b1100101 \
16
#1046000
b1100101 =
#1050000
06
#1055000
b1100110 #
b1100110 ]
b1100110 '
b1100110 _
b1100110 "
b1100110 \
16
#1056000
b1100110 =
#1060000
06
#1065000
b1100111 #
b1100111 ]
b1100111 '
b1100111 _
b1100111 "
b1100111 \
16
#1066000
b1100111 =
#1070000
06
#1075000
b1101000 #
b1101000 ]
b1101000 '
b1101000 _
b1101000 "
b1101000 \
16
#1076000
b1101000 =
#1080000
06
#1085000
b1101001 #
b1101001 ]
b1101001 '
b1101001 _
b1101001 "
b1101001 \
16
#1086000
b1101001 =
#1090000
06
#1095000
b1101010 #
b1101010 ]
b1101010 '
b1101010 _
b1101010 "
b1101010 \
16
#1096000
b1101010 =
#1100000
06
#1105000
b1101011 #
b1101011 ]
b1101011 '
b1101011 _
b1101011 "
b1101011 \
16
#1106000
b1101011 =
#1110000
06
#1115000
b1101100 #
b1101100 ]
b1101100 '
b1101100 _
b1101100 "
b1101100 \
16
#1116000
b1101100 =
#1120000
06
#1125000
b1101101 #
b1101101 ]
b1101101 '
b1101101 _
b1101101 "
b1101101 \
16
#1126000
b1101101 =
#1130000
06
#1135000
b1101110 #
b1101110 ]
b1101110 '
b1101110 _
b1101110 "
b1101110 \
16
#1136000
b1101110 =
#1140000
06
#1145000
b1101111 #
b1101111 ]
b1101111 '
b1101111 _
b1101111 "
b1101111 \
16
#1146000
b1101111 =
#1150000
06
#1155000
b1110000 #
b1110000 ]
b1110000 '
b1110000 _
b1110000 "
b1110000 \
16
#1156000
b1110000 =
#1160000
06
#1165000
b1110001 #
b1110001 ]
b1110001 '
b1110001 _
b1110001 "
b1110001 \
16
#1166000
b1110001 =
#1170000
06
#1175000
b1110010 #
b1110010 ]
b1110010 '
b1110010 _
b1110010 "
b1110010 \
16
#1176000
b1110010 =
#1180000
06
#1185000
b1110011 #
b1110011 ]
b1110011 '
b1110011 _
b1110011 "
b1110011 \
16
#1186000
b1110011 =
#1190000
06
#1195000
b1110100 #
b1110100 ]
b1110100 '
b1110100 _
b1110100 "
b1110100 \
16
#1196000
b1110100 =
#1200000
06
#1205000
b1110101 #
b1110101 ]
b1110101 '
b1110101 _
b1110101 "
b1110101 \
16
#1206000
b1110101 =
#1210000
06
#1215000
b1110110 #
b1110110 ]
b1110110 '
b1110110 _
b1110110 "
b1110110 \
16
#1216000
b1110110 =
#1220000
06
#1225000
b1110111 #
b1110111 ]
b1110111 '
b1110111 _
b1110111 "
b1110111 \
16
#1226000
b1110111 =
#1230000
06
#1235000
b1111000 #
b1111000 ]
b1111000 '
b1111000 _
b1111000 "
b1111000 \
16
#1236000
b1111000 =
#1240000
06
#1245000
b1111001 #
b1111001 ]
b1111001 '
b1111001 _
b1111001 "
b1111001 \
16
#1246000
b1111001 =
#1250000
06
#1255000
b1111010 #
b1111010 ]
b1111010 '
b1111010 _
b1111010 "
b1111010 \
16
#1256000
b1111010 =
#1260000
06
#1265000
b1111011 #
b1111011 ]
b1111011 '
b1111011 _
b1111011 "
b1111011 \
16
#1266000
b1111011 =
#1270000
06
#1275000
b1111100 #
b1111100 ]
b1111100 '
b1111100 _
b1111100 "
b1111100 \
16
#1276000
b1111100 =
#1280000
06
#1285000
b1111101 #
b1111101 ]
b1111101 '
b1111101 _
b1111101 "
b1111101 \
16
#1286000
b1111101 =
#1290000
06
